pdf_split_tool/__init__.py
pdf_split_tool/__main__.py
pdf_split_tool/file_handler.py
pdf_split_tool/pdf_splitter.py
pdf_split_tool/py.typed
pdf_split_tool-1.0.2.dist-info/entry_points.txt
pdf_split_tool-1.0.2.dist-info/LICENSE.rst
pdf_split_tool-1.0.2.dist-info/WHEEL
pdf_split_tool-1.0.2.dist-info/METADATA
pdf_split_tool-1.0.2.dist-info/RECORD
