Metadata-Version: 2.1
Name: pdf-split-tool
Version: 1.0.2
Summary: Pdf Split Tool
Home-page: https://github.com/staticdev/pdf-split-tool
License: MIT
Author: Thiago Carvalho D'Ávila
Author-email: thiagocavila@gmail.com
Requires-Python: >=3.8.0,<4.0.0
Classifier: License :: OSI Approved :: MIT License
Classifier: Programming Language :: Python
Classifier: Programming Language :: Python :: 3
Classifier: Programming Language :: Python :: 3.8
Classifier: Programming Language :: Python :: 3.9
Requires-Dist: PyPDF4 (>=1.27.0,<2.0.0)
Requires-Dist: click (>=7.0,<8.0)
Project-URL: Changelog, https://github.com/staticdev/pdf-split-tool/releases
Project-URL: Documentation, https://pdf-split-tool.readthedocs.io
Project-URL: Repository, https://github.com/staticdev/pdf-split-tool
